serox/__init__.py
serox/cmp.py
serox/common.py
serox/conftest.py
serox/convert.py
serox/default.py
serox/fmt.py
serox/iter.py
serox/misc.py
serox/option.py
serox/optional.py
serox/path.py
serox/prelude.py
serox/question_mark.py
serox/range.py
serox/result.py
serox/vec.py
serox/collections/__init__.py
serox/collections/hash_map.py
serox/collections/hash_set.py
serox-0.1.3.dist-info/METADATA
serox-0.1.3.dist-info/WHEEL
serox-0.1.3.dist-info/licenses/LICENSE.txt
serox-0.1.3.dist-info/RECORD
