Metadata-Version: 2.3
Name: serox
Version: 0.1.3
Summary: Serpentine Oxidation: Rusty abstractions for Python.
Author: Myles Bartlett
License: MIT
Keywords: iterators,monads,option,protocols,python,result,rust,structural-typing,traits,types,typing
Classifier: License :: OSI Approved :: MIT License
Classifier: Operating System :: OS Independent
Classifier: Programming Language :: Python :: 3.12
Classifier: Typing :: Typed
Requires-Python: >=3.12
Requires-Dist: joblib>=1.4.2
